teamwork_mcp/__init__.py
teamwork_mcp/async_utils.py
teamwork_mcp/base_tool.py
teamwork_mcp/compress_utils.py
teamwork_mcp/http_client.py
teamwork_mcp/http_server.py
teamwork_mcp/manifest_tool.py
teamwork_mcp/manifest_tool_server.py
teamwork_mcp/mcp_sse_client.py
teamwork_mcp/mcp_sse_server.py
teamwork_mcp/academic_tools/__init__.py
teamwork_mcp/academic_tools/arxiv_source.py
teamwork_mcp/academic_tools/arxiv_test.py
teamwork_mcp/academic_tools/pubmed_source.py
teamwork_mcp/academic_tools/pubmed_test.py
teamwork_mcp/dummy_tools/__init__.py
teamwork_mcp/dummy_tools/alpha_init_test.py
teamwork_mcp/dummy_tools/echo.py
teamwork_mcp/dummy_tools/echo_test.py
teamwork_mcp/rfft_tools/__init__.py
teamwork_mcp/rfft_tools/alpha_init_test.py
teamwork_mcp/rfft_tools/alpha_markdown.py
teamwork_mcp/rfft_tools/code_execution.py
teamwork_mcp/rfft_tools/code_execution_test.py
teamwork_mcp/rfft_tools/firecraw_search.py
teamwork_mcp/rfft_tools/firecraw_search_test.py
teamwork_mcp/rfft_tools/get_downloaded_files.py
teamwork_mcp/rfft_tools/get_downloaded_files_test.py
teamwork_mcp/rfft_tools/real_chrome_browser.py
teamwork_mcp/rfft_tools/real_chrome_browser_test.py
teamwork_mcp/rfft_tools/search_api_qwen.py
teamwork_mcp/rfft_tools/search_api_qwen_test.py
teamwork_mcp/rfft_tools/search_financial_mxc.py
teamwork_mcp/rfft_tools/search_financial_mxc_test.py
teamwork_mcp/rfft_tools/search_github.py
teamwork_mcp/rfft_tools/search_github_test.py
teamwork_mcp/rfft_tools/web_scrape.py
teamwork_mcp/rfft_tools/web_scrape_test.py
teamwork_mcp-0.3.3.dist-info/METADATA
teamwork_mcp-0.3.3.dist-info/WHEEL
teamwork_mcp-0.3.3.dist-info/top_level.txt
teamwork_mcp-0.3.3.dist-info/RECORD
