Metadata-Version: 2.4
Name: teamwork-mcp
Version: 0.3.3
Summary: SSE-based MCP Server and Client
Author-email: Qingxu Fu <fuqingxu.fqx@alibaba-inc.com>
License: UNKNOWN
Platform: UNKNOWN
Requires-Python: <3.12
Requires-Dist: anthropic>=0.45.1
Requires-Dist: argparse>=1.4.0
Requires-Dist: httpx>=0.28.1
Requires-Dist: mcp[cli]>=1.2.1
Requires-Dist: python-dotenv>=1.0.1
Requires-Dist: firecrawl-py>=1.14.1
Requires-Dist: loguru
Requires-Dist: pillow
Requires-Dist: regex
Requires-Dist: arxiv
Requires-Dist: tqdm
Requires-Dist: requests_oauthlib
Requires-Dist: astor
